neapolitan/__init__.py
neapolitan/views.py
neapolitan/management/__init__.py
neapolitan/management/commands/__init__.py
neapolitan/management/commands/mktemplate.py
neapolitan/templates/neapolitan/object_confirm_delete.html
neapolitan/templates/neapolitan/object_detail.html
neapolitan/templates/neapolitan/object_form.html
neapolitan/templates/neapolitan/object_list.html
neapolitan/templates/neapolitan/partial/detail.html
neapolitan/templates/neapolitan/partial/list.html
neapolitan/templatetags/__init__.py
neapolitan/templatetags/neapolitan.py
neapolitan-25.1.dist-info/LICENSE
neapolitan-25.1.dist-info/WHEEL
neapolitan-25.1.dist-info/METADATA
neapolitan-25.1.dist-info/RECORD
