Metadata-Version: 2.1
Name: neapolitan
Version: 25.1
Summary: Neapolitan: quick CRUD views for Django.
Author-email: Carlton Gibson <carlton.gibson@noumenal.es>
Classifier: License :: OSI Approved :: MIT License
Requires-Dist: Django
Requires-Dist: django-filter
Requires-Dist: Sphinx ; extra == "docs"
Requires-Dist: coverage[toml] ; extra == "tests"
Requires-Dist: django_coverage_plugin ; extra == "tests"
Project-URL: Docs, https://noumenal.es/neapolitan/
Project-URL: Repository, https://github.com/carltongibson/neapolitan
Provides-Extra: docs
Provides-Extra: tests
